tweet2png/__init__.py
tweet2png-0.1.0.dist-info/METADATA
tweet2png-0.1.0.dist-info/WHEEL
tweet2png-0.1.0.dist-info/top_level.txt
tweet2png-0.1.0.dist-info/RECORD
