Metadata-Version: 2.1
Name: tweet2png
Version: 0.1.0
Summary: turn tweet into png
Home-page: UNKNOWN
Author: abdouhl
License: MIT
Platform: UNKNOWN
